Workbook

Sheet Resumo Geral
A1: PAINEL DE CONTROLE FISCAL - DECLARAÇÃO DE IMPOSTO DE RENDA
A3: Visão consolidada dos rendimentos tributáveis, isentos, deduções e património declarado.
B5: RENDIMENTOS TRIBUTÁVEIS | D5: DEDUÇÕES LEGAIS | F5: PATRIMÓNIO DECLARADO
B6: =Rendimentos!F18 | D6: =Despesas_Dedutiveis!F18 | F6: =Bens_Direitos!F18
B9: DEMONSTRATIVO CONSOLIDADO PARA PREENCHIMENTO DO IRPF
B10: Categoria / Grupo | C10: Qtd. Itens | D10: Valor Consolidado (R$) | E10: Observação
B11: 1. Rendimentos Tributáveis Recebidos de PJ | C11: =COUNTA(Rendimentos!B6:B17) | D11: =Rendimentos!F18 | E11: Salários, pró-labore, 13º
B12: 2. IRRF Retido na Fonte (Compensável) | C12: =COUNTA(Rendimentos!B6:B17) | D12: =Rendimentos!G18 | E12: Imposto já pago retido em folha
B13: 3. Despesas Médicas e Odontológicas (100% dedutível) | C13: =COUNTIF(Despesas_Dedutiveis!C6:C17, "Saúde") | D13: =SUMIF(Despesas_Dedutiveis!C6:C17, "Saúde", Despesas_Dedutiveis!F6:F17) | E13: Sem limite legal de teto
B14: 4. Despesas com Educação / Instrução | C14: =COUNTIF(Despesas_Dedutiveis!C6:C17, "Educação") | D14: =SUMIF(Despesas_Dedutiveis!C6:C17, "Educação", Despesas_Dedutiveis!F6:F17) | E14: Sujeito ao limite individual anual
B15: 5. Previdência Privada (PGBL) | C15: =COUNTIF(Despesas_Dedutiveis!C6:C17, "Previdência (PGBL)") | D15: =SUMIF(Despesas_Dedutiveis!C6:C17, "Previdência (PGBL)", Despesas_Dedutiveis!F6:F17) | E15: Até 12% da renda bruta
B16: 6. Bens e Imóveis (Valor em 31/12) | C16: =COUNTA(Bens_Direitos!B6:B17) | D16: =Bens_Direitos!F18 | E16: Posição patrimonial informada

Sheet Rendimentos
A1: CONTROLE DE FONTES PAGADORAS E RENDIMENTOS
A5: Item | B5: CNPJ / CPF da Fonte | C5: Nome da Fonte Pagadora | D5: Tipo de Rendimento | E5: Titular / Dependente | F5: Rendimento Bruto (R$) | G5: IRRF Retido (R$)
A6: 1 | B6: 12.345.678/0001-90 | C6: Empresa Alpha Tecnologia Ltda | D6: Salário / Pró-labore | E6: Titular | F6: 78500 | G6: 11420
A7: 2 | B7: 98.765.432/0001-10 | C7: Beta Soluções e Serviços SA | D7: Prestação de Serviços | E7: Titular | F7: 14200 | G7: 1250
A8: 3 | B8: 00.000.000/0001-91 | C8: Banco do Brasil S.A. | D8: Rend. Isento (Poupança/LCI) | E8: Titular | F8: 2300 | G8: 0
A9: 4
A10: 5
A11: 6
A12: 7
A13: 8
A14: 9
A15: 10
A16: 11
A17: 12
A18: TOTAL DE RENDIMENTOS E RETENÇÃO: | F18: =SUM(F6:F17) | G18: =SUM(G6:G17)

Sheet Despesas_Dedutiveis
A1: LIVRO DE DESPESAS DEDUTÍVEIS (SAÚDE, EDUCAÇÃO, PREVIDÊNCIA)
A5: Item | B5: Data Despesa | C5: Categoria | D5: Prestador / Estabelecimento | E5: CNPJ / CPF do Prestador | F5: Valor Pago (R$) | G5: Comprovante / Recibo
A6: 1 | B6: 2026-02-15 | C6: Saúde | D6: Dr. Roberto Martins (Médico) | E6: 123.456.789-00 | F6: 650 | G6: Recibo nº 2026-01
A7: 2 | B7: 2026-03-20 | C7: Saúde | D7: Clínica Radiológica Central | E7: 11.222.333/0001-44 | F7: 420 | G7: NF-e 8812
A8: 3 | B8: 2026-04-10 | C8: Educação | D8: Faculdade Estácio | E8: 34.009.876/0001-20 | F8: 3890 | G8: Declaração de Quitação
A9: 4 | B9: 2026-11-28 | C9: Previdência (PGBL) | D9: Icatu Seguros SA | E9: 42.123.456/0001-88 | F9: 5000 | G9: Informe Anual Previdência
A10: 5
A11: 6
A12: 7
A13: 8
A14: 9
A15: 10
A16: 11
A17: 12
A18: TOTAL DE DESPESAS DEDUTÍVEIS: | F18: =SUM(F6:F17)

Sheet Bens_Direitos
A1: DECLARAÇÃO DE BENS E DIREITOS (PATRIMÓNIO)
A5: Item | B5: Código Receita | C5: Discriminação / Descrição Detalhada | D5: Localização / Instituição | E5: Situação Ano Anterior (R$) | F5: Situação Ano Atual (R$) | G5: Variação (R$)
A6: 1 | B6: 11 - Apartamento | C6: Apartamento residencial com 65m², financiado na CEF | D6: Salvador/BA | E6: 185000 | F6: 198000 | G6: =F6-E6
A7: 2 | B7: 21 - Veículo | C7: Veículo automotor marca GM Tracker ano 2024 | D7: Placa XYZ-9988 | E7: 85000 | F7: 85000 | G7: =F7-E7
A8: 3 | B8: 73 - Fundos Imobiliários | C8: 1500 cotas de FIIs diversos custodiados na corretora NuInvest | D8: XP / NuInvest | E8: 14500 | F8: 22800 | G8: =F8-E8
A9: 4 | G9: =F9-E9
A10: 5 | G10: =F10-E10
A11: 6 | G11: =F11-E11
A12: 7 | G12: =F12-E12
A13: 8 | G13: =F13-E13
A14: 9 | G14: =F14-E14
A15: 10 | G15: =F15-E15
A16: 11 | G16: =F16-E16
A17: 12 | G17: =F17-E17
A18: TOTAL DE BENS E DIREITOS: | E18: =SUM(E6:E17) | F18: =SUM(F6:F17) | G18: =F18-E18
