Workbook

Sheet Dashboard Vendas
A1: EXECUTIVE SALES DASHBOARD | DESEMPENHO COMERCIAL
B4: FATURAMENTO TOTAL | D4: TOTAL DE PEDIDOS | F4: TICKET MÉDIO | H4: VOLUME DE ITENS | J4: MARGEM MÉDIA ESTIMADA
B5: =SUM(Base_Vendas!G4:G33) | D5: =COUNTA(Base_Vendas!A4:A33) | F5: =B5/D5 | H5: =SUM(Base_Vendas!E4:E33) | J5: 0.245
B8: DESEMPENHO POR CATEGORIA DE PRODUTO | G8: DESEMPENHO POR REGIÃO / CANAL
B9: Categoria | C9: Qtd. Pedidos | D9: Receita Total (R$) | E9: Ticket Médio | G9: Região | H9: Qtd. Pedidos | I9: Receita (R$) | J9: Part. %
B10: Equipamentos | C10: =COUNTIF(Base_Vendas!C$4:C$33, "Equipamentos") | D10: =SUMIF(Base_Vendas!C$4:C$33, "Equipamentos", Base_Vendas!G$4:G$33) | E10: =D10/C10 | G10: Nordeste | H10: =COUNTIF(Base_Vendas!D$4:D$33, "Nordeste") | I10: =SUMIF(Base_Vendas!D$4:D$33, "Nordeste", Base_Vendas!G$4:G$33) | J10: =I10/$D$14
B11: Cabos & Conectores | C11: =COUNTIF(Base_Vendas!C$4:C$33, "Cabos & Conectores") | D11: =SUMIF(Base_Vendas!C$4:C$33, "Cabos & Conectores", Base_Vendas!G$4:G$33) | E11: =D11/C11 | G11: Sudeste | H11: =COUNTIF(Base_Vendas!D$4:D$33, "Sudeste") | I11: =SUMIF(Base_Vendas!D$4:D$33, "Sudeste", Base_Vendas!G$4:G$33) | J11: =I11/$D$14
B12: Serviços & Suporte | C12: =COUNTIF(Base_Vendas!C$4:C$33, "Serviços & Suporte") | D12: =SUMIF(Base_Vendas!C$4:C$33, "Serviços & Suporte", Base_Vendas!G$4:G$33) | E12: =D12/C12 | G12: Sul | H12: =COUNTIF(Base_Vendas!D$4:D$33, "Sul") | I12: =SUMIF(Base_Vendas!D$4:D$33, "Sul", Base_Vendas!G$4:G$33) | J12: =I12/$D$14
B13: Acessórios | C13: =COUNTIF(Base_Vendas!C$4:C$33, "Acessórios") | D13: =SUMIF(Base_Vendas!C$4:C$33, "Acessórios", Base_Vendas!G$4:G$33) | E13: =D13/C13 | G13: Centro-Oeste | H13: =COUNTIF(Base_Vendas!D$4:D$33, "Centro-Oeste") | I13: =SUMIF(Base_Vendas!D$4:D$33, "Centro-Oeste", Base_Vendas!G$4:G$33) | J13: =I13/$D$14
B14: TOTAL GERAL | C14: =SUM(C10:C13) | D14: =SUM(D10:D13) | E14: =D14/C14 | G14: TOTAL GERAL | H14: =SUM(H10:H13) | I14: =SUM(I10:I13) | J14: =SUM(J10:J13)

Sheet Base_Vendas
A1: BASE DE DADOS TRANSACIONAL DE VENDAS
A3: ID Pedido | B3: Data | C3: Categoria | D3: Região | E3: Qtd Vendida | F3: Preço Unitário (R$) | G3: Total Bruto (R$) | H3: Vendedor
A4: PED-1001 | B4: 2026-01-05 | C4: Equipamentos | D4: Nordeste | E4: 4 | F4: 1250 | G4: =E4*F4 | H4: Carlos Lima
A5: PED-1002 | B5: 2026-01-07 | C5: Cabos & Conectores | D5: Sudeste | E5: 25 | F5: 45 | G5: =E5*F5 | H5: Mariana Rios
A6: PED-1003 | B6: 2026-01-10 | C6: Serviços & Suporte | D6: Nordeste | E6: 2 | F6: 850 | G6: =E6*F6 | H6: Carlos Lima
A7: PED-1004 | B7: 2026-01-12 | C7: Acessórios | D7: Sul | E7: 10 | F7: 89.9 | G7: =E7*F7 | H7: Felipe Rocha
A8: PED-1005 | B8: 2026-01-15 | C8: Equipamentos | D8: Centro-Oeste | E8: 2 | F8: 2400 | G8: =E8*F8 | H8: Beatriz Souza
A9: PED-1006 | B9: 2026-01-18 | C9: Cabos & Conectores | D9: Nordeste | E9: 50 | F9: 38.5 | G9: =E9*F9 | H9: Carlos Lima
A10: PED-1007 | B10: 2026-01-20 | C10: Serviços & Suporte | D10: Sudeste | E10: 1 | F10: 1500 | G10: =E10*F10 | H10: Mariana Rios
A11: PED-1008 | B11: 2026-01-22 | C11: Acessórios | D11: Nordeste | E11: 15 | F11: 65 | G11: =E11*F11 | H11: Carlos Lima
A12: PED-1009 | B12: 2026-01-25 | C12: Equipamentos | D12: Sudeste | E12: 3 | F12: 1890 | G12: =E12*F12 | H12: Mariana Rios
A13: PED-1010 | B13: 2026-01-28 | C13: Cabos & Conectores | D13: Centro-Oeste | E13: 30 | F13: 42 | G13: =E13*F13 | H13: Beatriz Souza
A14: PED-1011 | B14: 2026-02-02 | C14: Serviços & Suporte | D14: Sul | E14: 3 | F14: 750 | G14: =E14*F14 | H14: Felipe Rocha
A15: PED-1012 | B15: 2026-02-04 | C15: Equipamentos | D15: Nordeste | E15: 5 | F15: 1100 | G15: =E15*F15 | H15: Carlos Lima
... A33: PED-1030 | B33: 2026-03-25 | C33: Cabos & Conectores | D33: Sudeste | E33: 55 | F33: 39 | G33: =E33*F33 | H33: Mariana Rios
A34: TOTAL CONSOLIDADO: | E34: =SUM(E4:E33) | F34: - | G34: =SUM(G4:G33)
